fabric_reports_client/__init__.py
fabric_reports_client/reports_api.py
fabric_reports_client-1.0.4.dist-info/licenses/LICENSE
fabric_reports_client-1.0.4.dist-info/WHEEL
fabric_reports_client-1.0.4.dist-info/METADATA
fabric_reports_client-1.0.4.dist-info/RECORD
