Metadata-Version: 2.4
Name: fabric_reports_client
Version: 1.0.4
Summary: FABRIC Reports Client API
Author-email: Komal Thareja <kthare10@renci.org>
Requires-Python: >=3.8
License-File: LICENSE
Requires-Dist: requests
